menace_ann/__init__.py
menace_ann/__main__.py
menace_ann-1.3.dist-info/METADATA
menace_ann-1.3.dist-info/WHEEL
menace_ann-1.3.dist-info/entry_points.txt
menace_ann-1.3.dist-info/top_level.txt
menace_ann-1.3.dist-info/RECORD
